LICENSE
MANIFEST.in
README.md
setup.py
imgcat/__init__.py
imgcat/__main__.py
imgcat/imgcat.py
imgcat/ipython_magic.py
imgcat/iterm2.py
imgcat/mpl_backend.py
imgcat/test_imgcat.py
imgcat.egg-info/PKG-INFO
imgcat.egg-info/SOURCES.txt
imgcat.egg-info/dependency_links.txt
imgcat.egg-info/entry_points.txt
imgcat.egg-info/not-zip-safe
imgcat.egg-info/requires.txt
imgcat.egg-info/top_level.txt