Metadata-Version: 2.1
Name: imgcat
Version: 0.6.0
Summary: imgcat as Python API and CLI
Home-page: https://github.com/wookayin/python-imgcat
Author: Jongwook Choi
Author-email: wookayin@gmail.com
License: MIT
Keywords: imgcat iterm2 matplotlib
Classifier: Development Status :: 3 - Alpha
Classifier: License :: OSI Approved :: MIT License
Classifier: Operating System :: POSIX :: Linux
Classifier: Programming Language :: Python :: 3.6
Classifier: Programming Language :: Python :: 3.7
Classifier: Programming Language :: Python :: 3.8
Classifier: Programming Language :: Python :: 3.9
Classifier: Programming Language :: Python :: 3.10
Classifier: Programming Language :: Python :: 3.11
Classifier: Programming Language :: Python :: 3.12
Requires-Python: >=3.6
Provides-Extra: test
License-File: LICENSE
